feedr/__init__.py
feedr/oauth2/__init__.py
feedr/oauth2/authorization_code.py
feedr/oauth2/client_credentials.py
feedr/oauth2/common.py
feedr/oauth2/device_code.py
feedr/oauth2/py.typed
feedr/oauth2/refresh_token.py
feedr/oauth2/test_imports.py
feedr.oauth2-0.1.3.dist-info/METADATA
feedr.oauth2-0.1.3.dist-info/WHEEL
feedr.oauth2-0.1.3.dist-info/top_level.txt
feedr.oauth2-0.1.3.dist-info/RECORD
