Metadata-Version: 2.1
Name: feedr.oauth2
Version: 0.1.3
Summary: Simple OAuth2 client.
Home-page: UNKNOWN
Author: Niklas Rosenstein
Author-email: rosensteinniklas@gmail.com
License: MIT
Platform: UNKNOWN
Requires-Python: >=3.5.0,<4.0.0
Requires-Dist: requests (<3.0.0,>=2.24.0)
Requires-Dist: databind.core (<1.0.0,>=0.6.0)
Requires-Dist: databind.json (<1.0.0,>=0.6.1)
